LICENSE
MANIFEST.in
README.rst
setup.cfg
setup.py
sunspear/__init__.py
sunspear/clients.py
sunspear/exceptions.py
sunspear.egg-info/PKG-INFO
sunspear.egg-info/SOURCES.txt
sunspear.egg-info/dependency_links.txt
sunspear.egg-info/not-zip-safe
sunspear.egg-info/requires.txt
sunspear.egg-info/top_level.txt
sunspear/activitystreams/__init__.py
sunspear/activitystreams/models.py
sunspear/aggregators/__init__.py
sunspear/aggregators/base.py
sunspear/aggregators/property.py
sunspear/backends/__init__.py
sunspear/backends/base.py
sunspear/backends/riak.py
sunspear/contrib/__init__.py
sunspear/contrib/circulators.py
sunspear/contrib/distributors.py
sunspear/lib/__init__.py
sunspear/lib/dotdict.py
sunspear/lib/rfc3339.py