Metadata-Version: 1.1
Name: sunspear
Version: 0.2.1
Summary: Activity streams backed by Riak.
Home-page: https://github.com/numan/sunspear
Author: Numan Sachwani
Author-email: numan856@gmail.com
License: Apache License 2.0
Platform: UNKNOWN
Classifier: Intended Audience :: Developers
Classifier: Intended Audience :: System Administrators
Classifier: Programming Language :: Python
Classifier: Topic :: Software Development
Classifier: Topic :: Utilities
